<?xml version="1.0" encoding="UTF-8"?>
<settings xmlns="http://maven.apache.org/SETTINGS/1.0.0"
          xmlns:xsi="http://www.w3.org/2001/XMLSchema-instance"
          xsi:schemaLocation="http://maven.apache.org/SETTINGS/1.0.0
                              https://maven.apache.org/xsd/settings-1.0.0.xsd">
    <localRepository/>
    <interactiveMode/>
    <usePluginRegistry/>
    <offline/>
    <servers>
		  <server>
            <id>smartbss-maven</id>
            <configuration>
                <httpHeaders>
                    <property>
                        <name>Authorization</name>
												<value>Basic </value>
                    </property>
                </httpHeaders>
            </configuration>
        </server>
    </servers>
    <mirrors/>
    <proxies/>
    <profiles>
        <profile>
            <id>default</id>

            <repositories>
                <repository>
                    <id>smartbss-maven</id>
                    <name>smartbss-maven</name>
										<url></url>
                    <layout>default</layout>
                    <snapshots>
                        <enabled>true</enabled>
                    </snapshots>
                </repository>
            </repositories>
        </profile>
    </profiles>
    <activeProfiles>
        <activeProfile>default</activeProfile>
    </activeProfiles>
</settings>

